.coveragerc
.readthedocs.yaml
LICENSE
MANIFEST.in
README.rst
environment.yml
pyproject.toml
setup.cfg
setup.py
climlab/__init__.py
climlab.egg-info/PKG-INFO
climlab.egg-info/SOURCES.txt
climlab.egg-info/dependency_links.txt
climlab.egg-info/top_level.txt
climlab/convection/__init__.py
climlab/convection/akmaev_adjustment.py
climlab/convection/convadj.py
climlab/convection/emanuel_convection.py
climlab/convection/simplified_betts_miller.py
climlab/domain/__init__.py
climlab/domain/axis.py
climlab/domain/domain.py
climlab/domain/field.py
climlab/domain/initial.py
climlab/domain/xarray.py
climlab/dynamics/__init__.py
climlab/dynamics/adv_diff_numerics.py
climlab/dynamics/advection_diffusion.py
climlab/dynamics/budyko_transport.py
climlab/dynamics/large_scale_condensation.py
climlab/dynamics/meridional_advection_diffusion.py
climlab/dynamics/meridional_heat_diffusion.py
climlab/dynamics/meridional_moist_diffusion.py
climlab/model/__init__.py
climlab/model/column.py
climlab/model/ebm.py
climlab/model/stommelbox.py
climlab/process/__init__.py
climlab/process/diagnostic.py
climlab/process/energy_budget.py
climlab/process/external_forcing.py
climlab/process/implicit.py
climlab/process/limiter.py
climlab/process/process.py
climlab/process/time_dependent_process.py
climlab/radiation/__init__.py
climlab/radiation/absorbed_shorwave.py
climlab/radiation/aplusbt.py
climlab/radiation/boltzmann.py
climlab/radiation/cam3.py
climlab/radiation/greygas.py
climlab/radiation/insolation.py
climlab/radiation/nband.py
climlab/radiation/radiation.py
climlab/radiation/transmissivity.py
climlab/radiation/water_vapor.py
climlab/radiation/rrtm/__init__.py
climlab/radiation/rrtm/rrtmg.py
climlab/radiation/rrtm/rrtmg_lw.py
climlab/radiation/rrtm/rrtmg_sw.py
climlab/radiation/rrtm/setup.py
climlab/radiation/rrtm/utils.py
climlab/solar/__init__.py
climlab/solar/insolation.py
climlab/solar/orbital_cycles.py
climlab/solar/orbital/__init__.py
climlab/solar/orbital/long.py
climlab/solar/orbital/setup.py
climlab/solar/orbital/table.py
climlab/surface/__init__.py
climlab/surface/albedo.py
climlab/surface/surface_radiation.py
