Metadata-Version: 2.2
Name: climlab
Version: 0.9.1
Summary: Package for process-oriented climate modeling
Home-page: http://github.com/climlab/climlab
Author: Brian E. J. Rose
Author-email: brose@albany.edu
License: MIT
Keywords: climate modeling modelling model ebm radiation radiative-convective earth
Classifier: License :: OSI Approved :: MIT License
Classifier: Programming Language :: Python
Classifier: Intended Audience :: Education
Classifier: Intended Audience :: Science/Research
Classifier: Topic :: Scientific/Engineering :: Atmospheric Science
License-File: LICENSE
Dynamic: author
Dynamic: author-email
Dynamic: classifier
Dynamic: description
Dynamic: home-page
Dynamic: keywords
Dynamic: license
Dynamic: summary
